foliant/config/downloadfile.py
foliantcontrib.downloadfile-1.0.1.dist-info/LICENSE
foliantcontrib.downloadfile-1.0.1.dist-info/METADATA
foliantcontrib.downloadfile-1.0.1.dist-info/WHEEL
foliantcontrib.downloadfile-1.0.1.dist-info/top_level.txt
foliantcontrib.downloadfile-1.0.1.dist-info/RECORD
